{
  "slug": "ochistiteli-stekol",
  "language": "ru",
  "meta": {
    "title": "Очиститель стекла авто — купить, цены | Ultimate",
    "description": "Очиститель стекла авто от производителя Ultimate. Удаление жира, пыли, отпечатков — спреи 500мл, 1л и 5л. Опт и розница."
  },
  "h1": "Очиститель стекла авто",
  "keywords_in_content": {
    "primary": ["очиститель стекла авто", "очиститель лобового стекла", "средство для стекол авто"],
    "secondary": ["очиститель стекол автомобиля", "средство для очистки стекол авто"],
    "supporting": ["средство для чистки стекол авто"]
  },
  "types": ["спреи", "без разводов"],
  "forms": ["готовый", "концентрат"],
  "volumes": ["500мл", "1л", "5л"],
  "updated_at": "2026-01-29"
}
