{
  "slug": "aksessuary-dlya-naneseniya",
  "language": "uk",
  "category_name_uk": "Аксесуари для нанесення",
  "clustered_at": "2025-12-30",
  "keywords": {
    "primary": [
      {"keyword": "губка для полірування авто", "keyword_ru": "губка для полировки авто", "volume": 170, "cluster": "main"},
      {"keyword": "аплікатор для авто", "keyword_ru": "аппликатор для авто", "volume": 30, "cluster": "main"}
    ],
    "secondary": [
      {"keyword": "губка для ручного полірування", "keyword_ru": "губка для ручной полировки авто", "volume": 10, "cluster": "type"},
      {"keyword": "губка з мікрофібри для авто", "keyword_ru": "губка из микрофибры для авто", "volume": 10, "cluster": "material"}
    ],
    "supporting": [
      {"keyword": "губка для салону авто", "keyword_ru": "губка для салона авто", "volume": 10, "cluster": "application"},
      {"keyword": "полірувальна губка", "keyword_ru": "полировочная губка для авто", "volume": 10, "cluster": "synonym"}
    ],
    "commercial": [
      {"keyword": "купити губку для полірування авто", "keyword_ru": "купить губку для полировки авто", "volume": 20, "cluster": "commercial", "use_in": "meta_only"}
    ]
  },
  "seo_titles": {"h1": "Аксесуари для нанесення", "main_keyword": "губка для полірування авто"},
  "translation_notes": {"adapted_terms": ["полировки→полірування", "аппликатор→аплікатор", "микрофибры→мікрофібри", "салона→салону", "полировочная→полірувальна"], "intent_preserved": true}
}
