{
  "slug": "podarochnyy",
  "language": "ru",
  "meta": {
    "title": "Подарочные наборы для мужчин в машину — купить, цены | Ultimate",
    "description": "Подарочные наборы для мужчин в машину от производителя Ultimate. Подарки для автолюбителей — комплекты автохимии в фирменной упаковке. Опт и розница."
  },
  "h1": "Подарочные наборы для мужчин в машину",
  "status": "generated",
  "updated_at": "2026-01-06",
  "keywords_in_content": {
    "primary": [
      "подарочные наборы для мужчин в машину",
      "подарочные наборы в машину",
      "подарочные наборы для автомобилиста"
    ]
  }
}
