{
  "slug": "mikrofibra-i-tryapki",
  "language": "ru",
  "meta": {
    "title": "Микрофибра для авто — купить в интернет-магазине Ultimate",
    "description": "Микрофибра для авто в интернет-магазине Ultimate. Для сушки, полировки, стекол — вафельные, twist, влаговпитывающие."
  },
  "h1": "Микрофибра для авто",
  "types": [
    "для сушки",
    "для полировки",
    "для стёкол"
  ],
  "forms": [
    "тряпки",
    "полотенца"
  ],
  "volumes": [
    "300 GSM",
    "600 GSM",
    "1200 GSM"
  ],
  "keywords_in_content": {
    "primary": [
      "микрофибра для авто",
      "тряпка для авто без разводов",
      "тряпка микрофибра для авто"
    ],
    "secondary": [
      "микрофибра для сушки авто",
      "микрофибра для полировки авто"
    ],
    "supporting": [
      "тряпки для сушки авто",
      "тряпки для сушки автомобиля"
    ]
  },
  "updated_at": "2026-01-19"
}
