{
  "slug": "zashchitnoe-pokrytie-dlya-koles",
  "language": "ru",
  "clustered_at": "2026-01-01",
  "parent": {
    "l1": "Мойка и Экстерьер",
    "l2": "Средства для дисков и шин"
  },
  "type": "category",
  "keywords": {
    "primary": [
      {
        "keyword": "защита дисков авто",
        "volume": 20,
        "cluster": "main",
        "original_section": "primary"
      },
      {
        "keyword": "защитное покрытие для дисков",
        "volume": 10,
        "cluster": "related",
        "original_section": "primary"
      },
      {
        "keyword": "защитное покрытие для литых дисков",
        "volume": 10,
        "cluster": "main",
        "original_section": "primary"
      }
    ]
  },
  "stats": {
    "before": 2,
    "after": 3,
    "total_volume": 40
  },
  "usage_rules": {
    "primary": "H1 + intro",
    "secondary": "H2 заголовки",
    "supporting": "FAQ, таблицы",
    "commercial": "ТОЛЬКО meta, НЕ в текст!"
  },
  "clustering_notes": {
    "proposed_changes": []
  }
}