{
  "slug": "nabory",
  "language": "uk",
  "meta": {
    "title": "Набір для хімчистки авто — купити, ціни | Ultimate",
    "description": "Набір для хімчистки авто від виробника Ultimate. Набори автохімії для детейлінгу, догляду за шкірою — готові комплекти. Опт і роздріб."
  },
  "h1": "Набір для хімчистки авто",
  "status": "updated",
  "updated_at": "2026-01-26",
  "keywords_in_content": {
    "primary": ["набір для хімчистки авто"],
    "secondary": ["набір автохімії", "набір для дітейлінгу"],
    "supporting": ["набір для догляду за шкіряним салоном", "набір щіток для дітейлінгу", "набір мікрофібри", "подарунковий набір для авто"]
  }
}
