{
  "id": "glavnaya",
  "name": "Головна сторінка",
  "language": "uk",
  "keywords": [
    {
      "keyword": "автокосметика",
      "volume": 590
    },
    {
      "keyword": "магазин автохімії",
      "volume": 390
    },
    {
      "keyword": "засоби для догляду за авто",
      "volume": 320
    },
    {
      "keyword": "купити активну піну",
      "volume": 210
    },
    {
      "keyword": "автохімія інтернет магазин",
      "volume": 170
    },
    {
      "keyword": "засоби догляду за авто",
      "volume": 170
    },
    {
      "keyword": "купити щітку для миття авто",
      "volume": 170
    },
    {
      "keyword": "купити щітку для миття автомобіля",
      "volume": 170
    },
    {
      "keyword": "автокосметика для авто",
      "volume": 140
    },
    {
      "keyword": "піна для авто",
      "volume": 140
    },
    {
      "keyword": "піна для автомобіля",
      "volume": 140
    },
    {
      "keyword": "набір для миття автомобіля",
      "volume": 140
    },
    {
      "keyword": "паста авто",
      "volume": 110
    },
    {
      "keyword": "преміум автохімія",
      "volume": 90
    },
    {
      "keyword": "професійна автохімія",
      "volume": 90
    },
    {
      "keyword": "автохімія опт",
      "volume": 90
    },
    {
      "keyword": "косметика для авто",
      "volume": 90
    },
    {
      "keyword": "косметика для автомобіля",
      "volume": 90
    },
    {
      "keyword": "піна для автомийки",
      "volume": 90
    },
    {
      "keyword": "купити хімію для авто",
      "volume": 90
    },
    {
      "keyword": "хімія для машини",
      "volume": 70
    },
    {
      "keyword": "хімія для миття машин",
      "volume": 70
    },
    {
      "keyword": "купити мікрофібру для авто",
      "volume": 70
    },
    {
      "keyword": "набір для мийки авто",
      "volume": 70
    },
    {
      "keyword": "автохімія для кузова",
      "volume": 50
    },
    {
      "keyword": "преміум мийка",
      "volume": 50
    },
    {
      "keyword": "автохімія київ",
      "volume": 40
    },
    {
      "keyword": "піна для машини",
      "volume": 40
    },
    {
      "keyword": "скотч малярний автомобільний",
      "volume": 40
    },
    {
      "keyword": "косметика для машин",
      "volume": 40
    },
    {
      "keyword": "купити піну для миття машини",
      "volume": 40
    },
    {
      "keyword": "купити хімію для мийки авто",
      "volume": 40
    },
    {
      "keyword": "магазин автокосметики",
      "volume": 40
    },
    {
      "keyword": "набір для догляду за машиною",
      "volume": 40
    },
    {
      "keyword": "набір для чистки автомобіля",
      "volume": 40
    },
    {
      "keyword": "набір для чистки салону авто",
      "volume": 40
    },
    {
      "keyword": "полірувальний набір для авто",
      "volume": 30
    },
    {
      "keyword": "догляд за салоном авто",
      "volume": 30
    },
    {
      "keyword": "хімія для безконтактної мийки авто",
      "volume": 30
    },
    {
      "keyword": "купити щітку для миття машини",
      "volume": 30
    },
    {
      "keyword": "набір для догляду за салоном автомобіля",
      "volume": 30
    },
    {
      "keyword": "автохімія",
      "volume": 20
    },
    {
      "keyword": "засіб для шкіряного салону",
      "volume": 20
    },
    {
      "keyword": "засіб для очищення скла автомобіля",
      "volume": 20
    },
    {
      "keyword": "засіб для скла авто",
      "volume": 20
    },
    {
      "keyword": "хімія для сидінь авто",
      "volume": 20
    },
    {
      "keyword": "купити хімію для чистки салону авто",
      "volume": 20
    },
    {
      "keyword": "купити щітку для машини",
      "volume": 20
    },
    {
      "keyword": "миючий засіб для авто",
      "volume": 20
    },
    {
      "keyword": "набір для прибирання машини",
      "volume": 20
    },
    {
      "keyword": "набір для чистки машини",
      "volume": 20
    },
    {
      "keyword": "нейтралізатори запаху",
      "volume": 20
    },
    {
      "keyword": "засіб для шкіри",
      "volume": 10
    },
    {
      "keyword": "засіб для очищення шкіри авто",
      "volume": 10
    },
    {
      "keyword": "засіб для очищення кузова авто",
      "volume": 10
    },
    {
      "keyword": "хімія для шкіри авто",
      "volume": 10
    },
    {
      "keyword": "хімія для чистки сидінь авто",
      "volume": 10
    },
    {
      "keyword": "каталог автокосметики",
      "volume": 10
    },
    {
      "keyword": "купити піну для мийки авто",
      "volume": 10
    },
    {
      "keyword": "набір для прибирання автомобіля",
      "volume": 10
    }
  ],
  "synonyms": [],
  "micro_intents": [
    "яка автокосметика краще",
    "як обрати автохімію",
    "топ засоби для догляду за авто"
  ],
  "total_volume": 4720
}
