{
  "slug": "obezzhirivateli",
  "language": "uk",
  "category_name_uk": "Знежирювачі",
  "category_name_ru": "Обезжириватели",
  "keywords": {
    "primary": [
      {
        "keyword": "знежирювачель для авто",
        "keyword_ru": "обезжириватель для авто",
        "volume": 100
      },
      {
        "keyword": "знежирювачель для кузова авто",
        "keyword_ru": "обезжириватель для кузова авто",
        "volume": 100
      },
      {
        "keyword": "знежирювачель для авто перед полировкой",
        "keyword_ru": "обезжириватель для авто перед полировкой",
        "volume": 100
      }
    ],
    "secondary": [
      {
        "keyword": "знежирювачель кузова перед полировкой",
        "keyword_ru": "обезжириватель кузова перед полировкой",
        "volume": 50
      }
    ],
    "supporting": [
      {
        "keyword": "знежирювачель для полировки авто",
        "keyword_ru": "обезжириватель для полировки авто",
        "volume": 20
      },
      {
        "keyword": "знежирювачель автомобильный",
        "keyword_ru": "обезжириватель автомобильный",
        "volume": 20
      }
    ],
    "commercial": [
      {
        "keyword": "купити знежирювачі",
        "keyword_ru": "купить обезжириватели",
        "volume": 100,
        "use_in": "meta_only"
      }
    ]
  },
  "translation_notes": {
    "adapted_terms": [
      [
        "резина",
        "гума"
      ],
      [
        "средство",
        "засіб"
      ],
      [
        "мойка",
        "миття"
      ],
      [
        "стекло",
        "скло"
      ],
      [
        "чернитель",
        "чорнитель"
      ]
    ],
    "kept_original": [
      "pH",
      "PPF",
      "APC",
      "SiO2"
    ],
    "intent_preserved": true
  }
}
